chromin-0.1.12.dist-info/METADATA
chromin-0.1.12.dist-info/WHEEL
chromin/__init__.py
chromin/chromin.cpython-312-x86_64-linux-gnu.so
chromin-0.1.12.dist-info/RECORD
