Metadata-Version: 2.4
Name: chromin
Version: 0.1.12
Classifier: Programming Language :: Rust
Classifier: Programming Language :: Python :: Implementation :: CPython
Classifier: Programming Language :: Python :: Implementation :: PyPy
Summary: High-performance terminal text coloring library for Python written in Rust.
Author-email: Basit Ahmad Ganie <basitahmed@1412.com>
Requires-Python: >=3.7
